getFN/__init__.py
getFN-1.1.dist-info/LICENSE
getFN-1.1.dist-info/METADATA
getFN-1.1.dist-info/WHEEL
getFN-1.1.dist-info/top_level.txt
getFN-1.1.dist-info/RECORD
