Metadata-Version: 2.1
Name: getFN
Version: 1.1
Summary: Lightweight module for get filenames & file exts
Home-page: https://www.beyonce.com/
Author: hunter g
Author-email: redissuslolol@gmail.com
License: UNKNOWN
Platform: UNKNOWN
Classifier: Programming Language :: Python :: 3
Classifier: License :: OSI Approved :: MIT License
Classifier: Operating System :: OS Independent
Requires-Python: >=3.6
